README
setup.py
bin/pamixer
pamixer/Client.py
pamixer/Curses.py
pamixer/ParCur.py
pamixer/PulseAudio.py
pamixer/Sample.py
pamixer/Sink.py
pamixer/SinkInput.py
pamixer/Source.py
pamixer/SourceOutput.py
pamixer/__init__.py
pamixer.egg-info/PKG-INFO
pamixer.egg-info/SOURCES.txt
pamixer.egg-info/dependency_links.txt
pamixer.egg-info/requires.txt
pamixer.egg-info/top_level.txt
pamixer/classes/SubVolume.py
pamixer/classes/__init__.py
pamixer/screens/ScreenClients.py
pamixer/screens/ScreenHelp.py
pamixer/screens/ScreenSamples.py
pamixer/screens/ScreenScripts.py
pamixer/screens/ScreenSinks.py
pamixer/screens/ScreenSources.py
pamixer/screens/ScreenVolume.py
pamixer/screens/__init__.py