Metadata-Version: 1.1
Name: pamixer
Version: 0.1.4
Summary: PulseAudio Curses Mixer Application
Home-page: http://github.com/valodim/pamixer
Author: Valodim
Author-email: valodim@mugenguild.com
License: UNKNOWN
Platform: UNKNOWN
Requires: libpulseaudio(>=1.1)
Requires: argparse
